cursword/__init__.py
cursword/cursword.py
cursword-0.1.1.dist-info/METADATA
cursword-0.1.1.dist-info/WHEEL
cursword-0.1.1.dist-info/licenses/LICENSE
cursword-0.1.1.dist-info/RECORD
