Metadata-Version: 2.4
Name: cursword
Version: 0.1.1
Summary: Simple functions to move by words in a string
Project-URL: Repository, https://github.com/ductorex/cursword
License-File: LICENSE
Requires-Python: >=3.13
